yarobot/__init__.py
yarobot/__main__.py
yarobot/app.py
yarobot/common.py
yarobot/config.py
yarobot/database.py
yarobot/generate.py
yarobot/rule_generator.py
yarobot/3rdparty/strings.xml
yarobot/static/android-chrome-192x192.png
yarobot/static/android-chrome-512x512.png
yarobot/static/apple-touch-icon.png
yarobot/static/favicon-16x16.png
yarobot/static/favicon-32x32.png
yarobot/static/favicon.ico
yarobot/templates/base.html
yarobot/templates/index.html
yarobot-0.5.3.dist-info/METADATA
yarobot-0.5.3.dist-info/WHEEL
yarobot-0.5.3.dist-info/entry_points.txt
yarobot-0.5.3.dist-info/licenses/LICENSE
yarobot-0.5.3.dist-info/RECORD
