Metadata-Version: 2.4
Name: yarobot
Version: 0.5.3
Summary: YARA generator inspired by yarGen
Project-URL: Homepage, https://github.com/ogre2007/yarobot
Project-URL: Issues, https://github.com/ogre2007/issues
Author-email: ogre2007 <oogre@vk.com>
License-Expression: GPL-3.0-only
License-File: LICENSE
Requires-Python: >=3.10
Requires-Dist: click>=8.3.0
Requires-Dist: flask>=3.1.2
Requires-Dist: lxml>=4.9.0
Requires-Dist: orjson>=3.11
Requires-Dist: pyopenssl
Requires-Dist: pyzipper>=0.3.6
Requires-Dist: stringzz>=0.4.3
